aydie_prompt_forge/__init__.py
aydie_prompt_forge/core.py
aydie_prompt_forge/exceptions.py
aydie_prompt_forge/models.py
aydie_prompt_forge-2.0.0.dist-info/METADATA
aydie_prompt_forge-2.0.0.dist-info/WHEEL
aydie_prompt_forge-2.0.0.dist-info/top_level.txt
aydie_prompt_forge-2.0.0.dist-info/RECORD
