Metadata-Version: 2.4
Name: aydie-prompt-forge
Version: 2.0.0
Summary: A modern toolkit for creating, managing, and testing LLM prompts as code.
Author-email: "Aditya (Aydie) Dinesh K" <developer@aydie.in>
License: MIT
Project-URL: Homepage, https://github.com/aydiegithub/aydie-prompt-forge
Project-URL: Bug Tracker, https://github.com/aydiegithub/aydie-prompt-forge/issues
Classifier: Programming Language :: Python :: 3
Classifier: License :: OSI Approved :: MIT License
Classifier: Operating System :: OS Independent
Classifier: Intended Audience :: Developers
Classifier: Topic :: Software Development :: Libraries :: Python Modules
Classifier: Topic :: Scientific/Engineering :: Artificial Intelligence
Requires-Python: >=3.8
Requires-Dist: pyyaml>=6.0
